{
  "categorias": [
    {
      "titulo": "Músicas",
      "link": "",
      "cor": "#000000",
      "link_extra": {
        "text": "",
        "url": ""
      },
      "videos": [
        {
          "titulo": "God of War - Trailer em Português | PS4",
          "url": "https://www.youtube.com/watch?v=FyIwEFXOcaE&t=18s"
        },
        {
          "titulo": "Lil Wayne - Mirror ft. Bruno Mars (Official Music Video)",
          "url": "https://www.youtube.com/watch?v=OZLUa8JUR18"
        },
        {
          "titulo": "Chris Brown - No Guidance (Official Video) ft. Drake",
          "url": "https://www.youtube.com/watch?v=6L_k74BOLag"
        },
        {
          "titulo": "Tyga - Taste (Official Video) ft. Offset",
          "url": "https://www.youtube.com/watch?v=LjxulQ1bEWg"
        },
        {
          "titulo": "Migos - Slippery feat. Gucci Mane [Official Video]",
          "url": "https://www.youtube.com/watch?v=Hm1YFszJWbQ"
        },
        {
          "titulo": "21 Savage, Offset, Metro Boomin - Ric Flair Drip (Official Music Video)",
          "url": "https://www.youtube.com/watch?v=LPTlvQ1Zet0"
        },
        {
          "titulo": "Lil Wayne - Love Me ft. Drake, Future (Explicit) (Official Music Video)",
          "url": "https://www.youtube.com/watch?v=KY44zvhWhp4"
        },
        {
          "titulo": "Young Thug - Check (Official Music Video)",
          "url": "https://www.youtube.com/watch?v=p0x6FEDV-ig"
        },
        {
          "titulo": "Kevin Gates - 2 Phones [Official Music Video]",
          "url": "https://www.youtube.com/watch?v=oiY_iKSpWLM"
        },
        {
          "titulo": "Chris Brown - Love More (Explicit) ft. Nicki Minaj",
          "url": "https://www.youtube.com/watch?v=Tff2oE31Mlw"
        }, 
        {
          "titulo": "SAINt JHN - Roses [Official Music Video]",
          "url": "https://www.youtube.com/watch?v=XHA-QM-q-3E"
        },
        {
          "titulo": "Future - Low Life (Official Music Video) ft. The Weeknd",
          "url": "https://www.youtube.com/watch?v=K_9tX4eHztY"
        },
        {
          "titulo": "Ty Dolla $ign - Or Nah ft. The Weeknd, Wiz Khalifa & DJ Mustard [Music Video]",
          "url": "https://www.youtube.com/watch?v=TUj0otkJEBo"
        },
        {
          "titulo": "Drake - Toosie Slide",
          "url": "https://www.youtube.com/watch?v=xWggTb45brM"
        },
        {
          "titulo": "Travis Scott - HIGHEST IN THE ROOM (Official Music Video)",
          "url": "https://www.youtube.com/watch?v=tfSS1e3kYeo"
        },
        {
          "titulo": "Roddy Ricch - The Box [Official Music Video]",
          "url": "https://www.youtube.com/watch?v=UNZqm3dxd2w"
        }
      ]
    },
    {
      "titulo": "Tecnologia",
      "cor": "#000000" ,
      "link_extra": {
        "text": "Cursos de Back End na Alura",
        "url": "https://www.alura.com.br/cursos-online-programacao"
      },
      "videos": [
        {
          "titulo": "PERCURSO em NÍVEL em ÁRVORE BINÁRIA | Estruturas de Dados #14",
          "url": "https://www.youtube.com/watch?v=UOK7nS2E9xM"
        },
        {
          "titulo": "Coders4Tips - S01E04: GitHub CLI - Uma Nova Experiência no Github!",
          "url": "https://www.youtube.com/watch?v=6o6-bKOZOEY"
        },
        {
          "titulo": "Programei 4 robôs que criam vídeos para mim no YouTube",
          "url": "https://www.youtube.com/watch?v=kjhu1LEmRpY"
        },
        {
          "titulo": "API: Dicionário do Programador",
          "url": "https://www.youtube.com/watch?v=vGuqKIRWosk"
        }, 
        {
          "titulo": "Usando Git Direito",
          "url": "https://www.youtube.com/watch?v=6OokP-NE49k"
        }
      ]
    },
    {
      "titulo": "Humor",
      "cor": "#000000",
      "link_extra": {
        "text": "Cursos de Data Science na Alura",
        "url": "https://www.alura.com.br/formacao-data-science"
      },
      "videos": [
        {
          "titulo": "Teste de Turing",
          "url": "https://www.youtube.com/watch?v=BaPGU4JWa34"
        },
        {
          "titulo": "O que é Data Science?",
          "url": "https://www.youtube.com/watch?v=5b9Z8toVaAU&t=9s"
        },
        {
          "titulo": "Melhor forma de aprender Python",
          "url": "https://www.youtube.com/watch?v=Gojqw9BQ5qY"
        },
        {
          "titulo": "Como ingressar no mercado de Data Science?",
          "url": "https://www.youtube.com/watch?v=gxyjGmOV540"
        }
      ]
    },
    {
      "titulo": "Filmes",
      "cor": "#000000",
      "videos": [
        {
          "titulo": "Interestellar",
          "url": "https://www.youtube.com/watch?v=frD_IiY_A3E"
        },
        {
          "titulo": "Gattaca",
          "url": "https://www.youtube.com/watch?v=Dl0tYLbrhhs"
        },
        {
          "titulo": "A Chegada",
          "url": "https://www.youtube.com/watch?v=rNciXGzYZms"
        },
        {
          "titulo": "Feitiço do Tempo",
          "url": "https://www.youtube.com/watch?v=zi8d69P9NvI"
        }
      ]
    },
    {
      "titulo": "Games",
      "cor": "#000000",
      "link_extra": {
        "text": "Formação de Jogos na Alura",
        "url": "https://www.alura.com.br/formacao-jogos-unity"
      },
      "videos": [
        {
          "titulo": "Final Fantasy 7",
          "url": "https://www.youtube.com/watch?v=I_ATSCTnUD8"
        },
        {
          "titulo": "Assassins Creed Valhalla",
          "url": "https://www.youtube.com/watch?v=KDfdjB9uL0U"
        },
        {
          "titulo": "God of War 4",
          "url": "https://www.youtube.com/watch?v=FyIwEFXOcaE"
        },
        {
          "titulo": "Resident Evil 8",
          "url": "https://www.youtube.com/watch?v=JSapXD9vxYA"
        },
        {
          "titulo": "Pokémon Let's Go Pikachu/Eevee",
          "url": "https://www.youtube.com/watch?v=L56q_k2ydrs"
        }
      ]
    },
    {
      "titulo": "Entretenimento",
      "cor": "#000000",
      "link_extra": {
        "text": "Curso sobre aprendizado na Alura",
        "url": "https://alura.com.br/curso-online-aprender-a-aprender-tecnicas-para-seu-autodesenvolvimento"
      },
      "videos": [
        {
          "titulo": "Como estudar melhor?",
          "url": "https://www.youtube.com/watch?v=Is6c9KSGCbk&feature=youtu.be"
        },
        {
          "titulo": "Faculdade",
          "url": "https://www.youtube.com/watch?v=jw06H8esyzQ&feature=youtu.be"
        },
        {
          "titulo": "Frameworks",
          "url": "https://www.youtube.com/watch?v=QzDjdlF1BQI"
        },
        {
          "titulo": "A mágica do Aprendizado",
          "url": "https://www.youtube.com/watch?v=oTEXzpfEpPY"
        },
        {
          "titulo": "Como aprender a programar?",
          "url": "https://www.youtube.com/watch?v=MwCx2qKdbDw&feature=youtu.be"
        }
      ]
    }
  ]
}